django_post_office-3.10.1.dist-info/licenses/AUTHORS.rst
django_post_office-3.10.1.dist-info/licenses/LICENSE.txt
post_office/__init__.py
post_office/admin.py
post_office/apps.py
post_office/backends.py
post_office/cache.py
post_office/connections.py
post_office/fields.py
post_office/lockfile.py
post_office/logutils.py
post_office/mail.py
post_office/models.py
post_office/sanitizer.py
post_office/settings.py
post_office/signals.py
post_office/tasks.py
post_office/utils.py
post_office/validators.py
post_office/version.py
post_office/views.py
post_office/locale/cs/LC_MESSAGES/django.po
post_office/locale/de/LC_MESSAGES/django.mo
post_office/locale/de/LC_MESSAGES/django.po
post_office/locale/es/LC_MESSAGES/django.mo
post_office/locale/es/LC_MESSAGES/django.po
post_office/locale/it/LC_MESSAGES/django.mo
post_office/locale/it/LC_MESSAGES/django.po
post_office/locale/pl/LC_MESSAGES/django.mo
post_office/locale/pl/LC_MESSAGES/django.po
post_office/locale/ru_RU/LC_MESSAGES/django.mo
post_office/locale/ru_RU/LC_MESSAGES/django.po
post_office/management/__init__.py
post_office/management/commands/__init__.py
post_office/management/commands/cleanup_mail.py
post_office/management/commands/send_queued_mail.py
post_office/migrations/0001_initial.py
post_office/migrations/0002_add_i18n_and_backend_alias.py
post_office/migrations/0003_longer_subject.py
post_office/migrations/0004_auto_20160607_0901.py
post_office/migrations/0005_auto_20170515_0013.py
post_office/migrations/0006_attachment_mimetype.py
post_office/migrations/0007_auto_20170731_1342.py
post_office/migrations/0008_attachment_headers.py
post_office/migrations/0009_requeued_mode.py
post_office/migrations/0010_message_id.py
post_office/migrations/0011_models_help_text.py
post_office/migrations/0012_alter_attachment_file_storage.py
post_office/migrations/0013_email_recipient_delivery_status_alter_log_status.py
post_office/migrations/__init__.py
post_office/template/__init__.py
post_office/template/backends/__init__.py
post_office/template/backends/post_office.py
post_office/templates/admin/post_office/email/change_form.html
django_post_office-3.10.1.dist-info/METADATA
django_post_office-3.10.1.dist-info/WHEEL
django_post_office-3.10.1.dist-info/top_level.txt
django_post_office-3.10.1.dist-info/RECORD
