Metadata-Version: 2.4
Name: django-post_office
Version: 3.10.1
Summary: A Django app to monitor and send mail asynchronously, complete with template support.
Author-email: Selwin Ong <selwin.ong@gmail.com>
License-Expression: MIT
Project-URL: Homepage, https://github.com/ui/django-post_office
Classifier: Development Status :: 5 - Production/Stable
Classifier: Environment :: Web Environment
Classifier: Framework :: Django
Classifier: Framework :: Django :: 4.2
Classifier: Framework :: Django :: 5.0
Classifier: Framework :: Django :: 5.1
Classifier: Framework :: Django :: 5.2
Classifier: Intended Audience :: Developers
Classifier: Operating System :: OS Independent
Classifier: Programming Language :: Python
Classifier: Programming Language :: Python :: 3
Classifier: Programming Language :: Python :: 3 :: Only
Classifier: Programming Language :: Python :: 3.9
Classifier: Programming Language :: Python :: 3.10
Classifier: Programming Language :: Python :: 3.11
Classifier: Programming Language :: Python :: 3.12
Classifier: Programming Language :: Python :: 3.13
Classifier: Topic :: Communications :: Email
Classifier: Topic :: Internet :: WWW/HTTP
Classifier: Topic :: Software Development :: Libraries :: Python Modules
Requires-Python: >=3.9
License-File: LICENSE.txt
License-File: AUTHORS.rst
Requires-Dist: bleach[css]
Requires-Dist: django>=4.2
Provides-Extra: test
Requires-Dist: tox>=2.3; extra == "test"
Provides-Extra: prevent-xss
Requires-Dist: bleach; extra == "prevent-xss"
Dynamic: license-file
